image_optimizer_lib/__init__.py
image_optimizer_lib/resize.py
image_optimizer_lib-0.1.0.dist-info/licenses/LICENSE
image_optimizer_lib-0.1.0.dist-info/METADATA
image_optimizer_lib-0.1.0.dist-info/WHEEL
image_optimizer_lib-0.1.0.dist-info/top_level.txt
image_optimizer_lib-0.1.0.dist-info/RECORD
